{
	"global": {
		"settings": {
			"color": {
				"palette": [
					{
						"slug": "light",
						"color": "#f5f7f9"
					},
					{
						"slug": "dark",
						"color": "#000"
					}
				],
				"custom": false
			},
			"typography": {
				"fontSizes": [
					{
						"slug": "small",
						"size": "calc(12px + 0.8vw)"
					},
					{
						"slug": "normal",
						"size": "calc(17px + 0.8vw)"
					},
					{
						"slug": "medium",
						"size": "calc(23px + 0.8vw)"
					},
					{
						"slug": "large",
						"size": "calc(31px + 0.8vw)"
					},
					{
						"slug": "huge",
						"size": "calc(41px + 0.8vw)"
					}
				],
				"fontFamilies": [
					{
						"fontFamily": "-apple-system,BlinkMacSystemFont,\"Segoe UI\",Roboto,Oxygen-Sans,Ubuntu,Cantarell,\"Helvetica Neue\",sans-serif",
						"slug": "system",
						"name": "System",
						"group": "web-safe"
					},
					{
						"fontFamily": "serif",
						"name": "Serif",
						"slug": "serif",
						"group": "web-safe"
					},
					{
						"fontFamily": "monospace",
						"name": "Monospace",
						"slug": "monospace",
						"group": "web-safe"
					}
				],
				"fontFamilyGroups": [
					{
						"name": "Web safe",
						"slug": "web-safe"
					}
				],
				"customFontSize": false,
				"customLineHeight": true
			}
		},
		"styles": {
			"color": {
				"background": "var(--wp--preset--color--background)",
				"text": "var(--wp--preset--color--text)",
				"link": "var(--wp--preset--color--text)"
			}
		}
	},
	"core/paragraph": {
		"styles": {
			"color": {
				"link": "var(--wp--preset--color--text)",
				"text": "var(--wp--preset--color--text)"
			},
			"typography": {
				"fontSize": "var(--wp--preset--font-size--normal)",
				"lineHeight": "1.55",
				"fontFamily": "var(--wp--preset--font-family--system)"
			}
		}
	},
	"core/heading/h1": {
		"styles": {
			"typography": {
				"fontSize": "var(--wp--preset--font-size--huge)",
				"lineHeight": "1.4",
				"fontFamily": "var(--wp--preset--font-family--system)"
			}
		}
	},
	"core/heading/h2": {
		"styles": {
			"typography": {
				"fontSize": "var(--wp--preset--font-size--large)",
				"lineHeight": "1.4",
				"fontFamily": "var(--wp--preset--font-family--system)"			
			}
		}
	},
	"core/heading/h3": {
		"styles": {
			"typography": {
				"fontSize": "var(--wp--preset--font-size--medium)",
				"lineHeight": "1.55",
				"fontFamily": "var(--wp--preset--font-family--system)"
			}
		}
	},
	"core/heading/h4": {
		"styles": {
			"typography": {
				"fontSize": "var(--wp--preset--font-size--normal)",
				"lineHeight": "1.55",
				"fontFamily": "var(--wp--preset--font-family--system)"
			}
		}
	},
	"core/heading/h5": {
		"styles": {
			"typography": {
				"fontSize": "var(--wp--preset--font-size--small)",
				"lineHeight": "1.8",
				"fontFamily": "var(--wp--preset--font-family--system)"
			}
		}
	},
	"core/heading/h6": {
		"styles": {
			"typography": {
				"fontSize": "var(--wp--preset--font-size--small)",
				"lineHeight": "1.8",
				"fontFamily": "var(--wp--preset--font-family--system)"
			}
		}
	},
	"core/columns": {
		"styles": {
			"color": {
				"link": "var(--wp--preset--color--text)",
				"text": "var(--wp--preset--color--text)"
			}
		}
	},
	"core/group": {
		"styles": {
			"color": {
				"link": "var(--wp--preset--color--text)",
				"text": "var(--wp--preset--color--text)"
			}
		}
	},
	"core/media-text": {
		"styles": {
			"color": {
				"link": "var(--wp--preset--color--text)",
				"text": "var(--wp--preset--color--text)"
			}
		}
	}
}